{"nodes": [{"id": "TestPlanValidationFailure", "label": "Test Failure: Plan 400 Validation", "file_type": "rationale", "source_file": "test-results/membership-plans-Membershi-2008a-reate-a-plan-via-direct-URL-api-tests/error-context.md", "source_location": null, "source_url": null, "captured_at": null, "author": null, "contributor": null}], "edges": [{"source": "PlaywrightTests", "target": "TestPlanValidationFailure", "relation": "conceptually_related_to", "confidence": "EXTRACTED", "confidence_score": 1.0, "source_file": "test-results/membership-plans-Membershi-2008a-reate-a-plan-via-direct-URL-api-tests/error-context.md", "source_location": null, "weight": 1.0}, {"source": "TestPlanValidationFailure", "target": "MembershipService", "relation": "conceptually_related_to", "confidence": "EXTRACTED", "confidence_score": 1.0, "source_file": "test-results/membership-plans-Membershi-2008a-reate-a-plan-via-direct-URL-api-tests/error-context.md", "source_location": null, "weight": 1.0}], "hyperedges": []}